SATRL/__init__.py
SATRL/_learner.py
SATRL/test/__init__.py
SATRL/test/test_import.py
satrl-0.0.1.dist-info/METADATA
satrl-0.0.1.dist-info/WHEEL
satrl-0.0.1.dist-info/top_level.txt
satrl-0.0.1.dist-info/RECORD
