Metadata-Version: 2.4
Name: SATRL
Version: 0.0.1
Summary: Simple RL baseline library
Requires-Python: >=3.8
